{
  "headline": "국내증시 강세, 휴머노이드로봇주 급등 주도",
  "market": "KOSPI가 8,476으로 3.55% 상승하며 강한 흐름을 보인 반면, KOSDAQ은 1,075로 2.68% 하락했습니다. 미국 지표(S&P500 +0.58%, NASDAQ +0.91%)는 완만한 상승이나, 국내 주식시장이 글로벌 대비 우수한 성과를 기록했습니다.",
  "holdings": "TIGER 코리아휴머노이드로봇산업이 8.84% 급등하며 포트폴리오 상승을 주도했고, 삼성전자도 5.84% 올랐습니다. 반면 방산주(한화에어로스페이스 -2.25%)와 금융주(DB증권 -1.08%)가 약세를 보였습니다.",
  "sectors": "반도체 및 AI 관련 로봇산업이 강세를 이끌고 있는 반면, 방산·증권 섹터는 부진하고 있습니다.",
  "news": "주요 악재 뉴스 없이 AI·로봇 섹터의 긍정적 심리가 시장을 주도하고 있으며, 호재 뉴스 8건이 악재 2건을 압도하고 있습니다.",
  "action": "로봇·AI 업종의 강세세가 지속되는 만큼 해당 비중을 유지하되, 하락한 방산주는 추가 하락 신호 확인 후 조정 여부를 판단하세요.",
  "mood": "positive",
  "generated_at": "2026-05-29 14:46",
  "realtime": false
}